dasb_translator/__init__.py
dasb_translator-0.0.4.dist-info/LICENSE
dasb_translator-0.0.4.dist-info/METADATA
dasb_translator-0.0.4.dist-info/WHEEL
dasb_translator-0.0.4.dist-info/entry_points.txt
dasb_translator-0.0.4.dist-info/top_level.txt
dasb_translator-0.0.4.dist-info/RECORD
