Metadata-Version: 2.1
Name: dasb-translator
Version: 0.0.4
Summary: A CLI translation tool by reading the clipboard
Home-page: https://github.com/Acoustical/Dasb_Translator
Author: Hompeaz
Author-email: hompeaz@gmail.com
Classifier: Programming Language :: Python :: 3
Classifier: License :: OSI Approved :: MIT License
Classifier: Operating System :: OS Independent
License-File: LICENSE
Requires-Dist: requests
Requires-Dist: pyperclip
Requires-Dist: deepl-cli
